poniard/__init__.py
poniard/_modidx.py
poniard/_version.py
poniard/error_analysis/__init__.py
poniard/error_analysis/error_analysis.py
poniard/estimators/__init__.py
poniard/estimators/classification.py
poniard/estimators/core.py
poniard/estimators/regression.py
poniard/plot/__init__.py
poniard/plot/plot_factory.py
poniard/plugins/__init__.py
poniard/plugins/core.py
poniard/plugins/pandas_profiling.py
poniard/plugins/wandb.py
poniard/preprocessing/__init__.py
poniard/preprocessing/categorical.py
poniard/preprocessing/core.py
poniard/preprocessing/datetime.py
poniard/utils/__init__.py
poniard/utils/estimate.py
poniard/utils/hyperparameters.py
poniard/utils/stats.py
poniard/utils/utils.py
tests/__init__.py
tests/test_add_remove.py
tests/test_core.py
tests/test_ensemble.py
tests/test_preprocessing.py
tests/test_tune.py
poniard-0.5.0.dist-info/LICENSE
poniard-0.5.0.dist-info/METADATA
poniard-0.5.0.dist-info/WHEEL
poniard-0.5.0.dist-info/entry_points.txt
poniard-0.5.0.dist-info/top_level.txt
poniard-0.5.0.dist-info/RECORD
