Metadata-Version: 2.1
Name: poniard
Version: 0.5.0
Summary: Streamline scikit-learn model comparison
Home-page: https://github.com/rxavier/poniard
Author: Rafael Xavier
Author-email: rxaviermontero@gmail.com
License: MIT
Keywords: machine learning,scikit-learn
Platform: UNKNOWN
Classifier: Development Status :: 4 - Beta
Classifier: Intended Audience :: Science/Research
Classifier: Intended Audience :: Developers
Classifier: Intended Audience :: End Users/Desktop
Classifier: Topic :: Scientific/Engineering
Classifier: Topic :: Scientific/Engineering :: Artificial Intelligence
Classifier: License :: OSI Approved :: MIT License
Classifier: Programming Language :: Python :: 3
Classifier: Programming Language :: Python :: 3.7
Classifier: Programming Language :: Python :: 3.8
Classifier: Programming Language :: Python :: 3.9
Classifier: Programming Language :: Python :: 3.10
Classifier: Operating System :: OS Independent
Requires-Python: >=3.7
Requires-Dist: xgboost (>=1.5.0)
Requires-Dist: pandas (>=1.3.5)
Requires-Dist: plotly
Requires-Dist: tqdm
Requires-Dist: scikit-learn (>=1.0.2) ; python_version < "3.8"
Requires-Dist: scikit-learn (>=1.1.0) ; python_version >= "3.8"
Requires-Dist: numpy (>=1.22.0) ; python_version >= "3.8"
Provides-Extra: dev
Requires-Dist: pytest ; extra == 'dev'
Requires-Dist: tox ; extra == 'dev'
Requires-Dist: tox-gh-actions ; extra == 'dev'
Requires-Dist: jupyter ; extra == 'dev'
Requires-Dist: ipywidgets (<8.0.0) ; extra == 'dev'
Requires-Dist: black[jupyter] ; extra == 'dev'
Requires-Dist: pre-commit ; extra == 'dev'
Requires-Dist: nbdev (>=2.3.9) ; extra == 'dev'
Requires-Dist: wandb ; extra == 'dev'
Requires-Dist: pandas-profiling (>=3.3.0) ; extra == 'dev'
